richkit/__init__.py
richkit/analyse/__init__.py
richkit/analyse/analyse.py
richkit/analyse/segment.py
richkit/analyse/util.py
richkit/lookup/__init__.py
richkit/lookup/geo.py
richkit/lookup/util.py
richkit/retrieve/__init__.py
richkit/retrieve/cert_sh.py
richkit/retrieve/ctlogs.py
richkit/retrieve/dns.py
richkit/retrieve/symantec.py
richkit/retrieve/urlvoid.py
richkit/retrieve/whois.py
richkit/retrieve/x509.py
richkit/test/__init__.py
richkit/test/analyse/__init__.py
richkit/test/analyse/test_analyse.py
richkit/test/lookup/__init__.py
richkit/test/lookup/test_geo.py
richkit/test/lookup/test_util.py
richkit/test/retrieve/__init__.py
richkit/test/retrieve/test_ctlogs.py
richkit/test/retrieve/test_dns.py
richkit/test/retrieve/test_symantec.py
richkit/test/retrieve/test_urlvoid.py
richkit/test/retrieve/test_whois.py
richkit/test/retrieve/test_x509.py
richkit-1.1.1.dist-info/LICENSE
richkit-1.1.1.dist-info/METADATA
richkit-1.1.1.dist-info/WHEEL
richkit-1.1.1.dist-info/top_level.txt
richkit-1.1.1.dist-info/RECORD
