Metadata-Version: 2.1
Name: richkit
Version: 1.1.1
Summary: Domain enrichment kit 
Home-page: https://github.com/aau-network-security/richkit
Author: ['Ahmet Turkmen', 'Gian Marco Mennecozzi ', 'Egon Kidmose']
License: UNKNOWN
Project-URL: Bug Reports, https://github.com/aau-network-security/richkit/issues
Project-URL: Funding, https://donate.pypi.org
Project-URL: Source, https://github.com/aau-network-security/richkit
Platform: UNKNOWN
Classifier: Development Status :: 4 - Beta
Classifier: Intended Audience :: Developers
Classifier: License :: OSI Approved :: MIT License
Classifier: Programming Language :: Python :: 3.5
Classifier: Programming Language :: Python :: 3.6
Classifier: Programming Language :: Python :: 3.7
Requires-Python: >=3.5
Requires-Dist: maxminddb
Requires-Dist: numpy (==1.17.2)
Requires-Dist: scikit-learn (==0.21.3)
Requires-Dist: langid (==1.1.6)
Requires-Dist: bs4 (==0.0.1)
Requires-Dist: lxml (==4.4.1)
Requires-Dist: requests (==2.22.0)
Requires-Dist: pytest
Requires-Dist: dnspython
Requires-Dist: coverage
